ndcc/__init__.py
ndcc/compare.py
ndcc/data/charts.csv
ndcc/input.py
ndcc/main.py
ndcc/validate.py
ndcc-0.2.0.dist-info/LICENSE
ndcc-0.2.0.dist-info/METADATA
ndcc-0.2.0.dist-info/WHEEL
ndcc-0.2.0.dist-info/entry_points.txt
ndcc-0.2.0.dist-info/RECORD
