Metadata-Version: 2.1
Name: ndcc
Version: 0.2.0
Summary: tba
License: MIT
Author: iron3oxide
Author-email: jason.hottelet@tuta.io
Requires-Python: >=3.10,<4.0
Classifier: License :: OSI Approved :: MIT License
Classifier: Programming Language :: Python :: 3
Classifier: Programming Language :: Python :: 3.10
Classifier: Programming Language :: Python :: 3.11
Requires-Dist: pandas (>=1.4.3,<2.0.0)
Requires-Dist: prompt-toolkit (>=3.0.30,<4.0.0)
Requires-Dist: rich (>=12.5.1,<13.0.0)
